README.md
setup.py
test/__init__.py
test/test_zconfig.py
test/test_zfile.py
test/test_zgeo.py
test/test_zmongo.py
test/test_zmysql.py
test/test_zredis.py
test/test_zalioss/__init__.py
test/test_zalioss/test_oss_config.py
test/zarea_matcher/__init__.py
test/zarea_matcher/test_area_matcher.py
test/zdict/__init__.py
test/zdict/test_dict_extract.py
test/zdict/test_dict_recursive_get.py
test/zjson/__init__.py
test/zjson/test_jsondumps.py
test/zrandom/__init__.py
test/zrandom/test_randhex.py
test/zrandom/test_randint.py
test/ztime/__init__.py
test/ztime/test_get_date.py
test/ztime/test_get_month.py
zzpy/__init__.py
zzpy/zalioss.py
zzpy/zarea_matcher.py
zzpy/zconfig.py
zzpy/zdefinition.py
zzpy/zdict.py
zzpy/zes.py
zzpy/zfile.py
zzpy/zfunction.py
zzpy/zgeo.py
zzpy/zjson.py
zzpy/zlist.py
zzpy/zmongo.py
zzpy/zmysql.py
zzpy/zprogress.py
zzpy/zrandom.py
zzpy/zredis.py
zzpy/zsys.py
zzpy/ztime.py
zzpy.egg-info/PKG-INFO
zzpy.egg-info/SOURCES.txt
zzpy.egg-info/dependency_links.txt
zzpy.egg-info/requires.txt
zzpy.egg-info/top_level.txt