Metadata-Version: 1.0
Name: zzpy
Version: 1.1.57
Summary: Python3 utilities
Home-page: https://github.com/zerocpp/zzpy
Author: zerocpp
Author-email: 85642468@qq.com
License: MIT Licence
Keywords: pip,zzpy,utils
Platform: any
